whatsapp_linkify/__init__.py
whatsapp_linkify/main.py
whatsapp_linkify/prompts.py
whatsapp_linkify-2025.12.21184318.dist-info/METADATA
whatsapp_linkify-2025.12.21184318.dist-info/WHEEL
whatsapp_linkify-2025.12.21184318.dist-info/top_level.txt
whatsapp_linkify-2025.12.21184318.dist-info/RECORD
