Metadata-Version: 2.4
Name: whatsapp-linkify
Version: 2025.12.21184318
Summary: Transforms phone numbers into direct WhatsApp chat links for easy conversations.
Author-email: whatsapp-linkify <hi@eugene.plus>
License: MIT
Project-URL: Homepage, https://github.com/chigwell/whatsapp-linkify
Requires-Python: >=3.9
Requires-Dist: langchain-llm7>=0.0.0
Requires-Dist: llmatch-messages>=0.0.0
Requires-Dist: langchain-core>=0.3.0
